samudra_ai/__init__.py
samudra_ai/core.py
samudra_ai/data_loader.py
samudra_ai/evaluator.py
samudra_ai/model2.py
samudra_ai/models.py
samudra_ai/preprocess_dcpp.py
samudra_ai/trainer.py
samudra_ai/utils.py
samudra_ai-1.3.3.dist-info/licenses/LICENSE
samudra_ai-1.3.3.dist-info/METADATA
samudra_ai-1.3.3.dist-info/WHEEL
samudra_ai-1.3.3.dist-info/top_level.txt
samudra_ai-1.3.3.dist-info/RECORD
