Metadata-Version: 2.4
Name: samudra-ai
Version: 1.3.3
Summary: Paket Python untuk pengolahan koreksi bias model iklim global menggunakan deep learning CNN-BiLSTM dan CONVLSTM2D.
Author-email: Adityo Wicaksono <adityo.wicaksono@bmkg.go.id>
License: MIT License
Project-URL: Homepage, https://github.com/adityoAJA/samudra-ai
Project-URL: Bug Tracker, https://github.com/adityoAJA/samudra-ai/issues
Classifier: Development Status :: 3 - Alpha
Classifier: Programming Language :: Python :: 3
Classifier: License :: OSI Approved :: MIT License
Classifier: Operating System :: OS Independent
Classifier: Intended Audience :: Science/Research
Classifier: Topic :: Scientific/Engineering :: Atmospheric Science
Classifier: Topic :: Scientific/Engineering :: Artificial Intelligence
Requires-Python: >=3.9
License-File: LICENSE
Requires-Dist: xarray
Requires-Dist: numpy
Requires-Dist: pandas
Requires-Dist: tensorflow==2.16.1
Requires-Dist: scikit-learn
Requires-Dist: matplotlib
Requires-Dist: h5netcdf
Requires-Dist: netCDF4
Requires-Dist: cftime
Requires-Dist: scikit-image
Requires-Dist: joblib
Requires-Dist: seaborn
Requires-Dist: scipy
Requires-Dist: openpyxl
Requires-Dist: cartopy
Dynamic: license-file
